README.md
setup.py
waveml/__init__.py
waveml/errors.py
waveml/main.py
waveml/metrics.py
waveml/utils.py
waveml.egg-info/PKG-INFO
waveml.egg-info/SOURCES.txt
waveml.egg-info/dependency_links.txt
waveml.egg-info/requires.txt
waveml.egg-info/top_level.txt