Metadata-Version: 2.1
Name: waveml
Version: 0.2.1
Summary: Open source machine learning library with various models and tools
Home-page: https://github.com/leffff/waveml
Author: leffff
Author-email: levnovitskiy@gmail.com
License: Apache License 2.0
Platform: UNKNOWN
Classifier: Programming Language :: Python :: 3
Classifier: Operating System :: OS Independent
Requires-Python: >=3.6
